atomsql/__init__.py
atomsql/db.py
atomsql/exceptions.py
atomsql/fields.py
atomsql/models.py
atomsql/query.py
atomsql/backends/__init__.py
atomsql/backends/base.py
atomsql/backends/postgres.py
atomsql/backends/sqlite.py
atomsql-0.0.2.dist-info/licenses/LICENSE
atomsql-0.0.2.dist-info/METADATA
atomsql-0.0.2.dist-info/WHEEL
atomsql-0.0.2.dist-info/top_level.txt
atomsql-0.0.2.dist-info/RECORD
