Metadata-Version: 2.4
Name: atomsql
Version: 0.0.2
Summary: A lightweight Object-Relational Mapping (ORM) library for Python with support for SQLite and PostgreSQL
Author: Prashant Singh
Author-email: Prashant Singh <box_prashant@outlook.com>
License-Expression: MIT
Project-URL: Homepage, https://github.com/prashant-fintech/atomsql
Project-URL: Repository, https://github.com/prashant-fintech/atomsql
Project-URL: Issues, https://github.com/prashant-fintech/atomsql/issues
Keywords: orm,database,sqlite,postgresql,sql
Classifier: Development Status :: 3 - Alpha
Classifier: Intended Audience :: Developers
Classifier: Programming Language :: Python :: 3
Classifier: Programming Language :: Python :: 3.12
Classifier: Topic :: Database
Classifier: Topic :: Software Development :: Libraries :: Python Modules
Requires-Python: >=3.12
License-File: LICENSE
Requires-Dist: psycopg[binary]>=3.3.2
Dynamic: author
Dynamic: license-file
